green_lib/__init__.py
green_lib-1.0.0.dist-info/LICENSE
green_lib-1.0.0.dist-info/METADATA
green_lib-1.0.0.dist-info/WHEEL
green_lib-1.0.0.dist-info/top_level.txt
green_lib-1.0.0.dist-info/RECORD
